drkns/__init__.py
drkns/cli/__init__.py
drkns/configunit/ConfigUnit.py
drkns/configunit/__init__.py
drkns/configunit/get_error_string.py
drkns/configunit/get_hash.py
drkns/configunit/load.py
drkns/context/Context.py
drkns/context/__init__.py
drkns/context/clean_persistence_files.py
drkns/context/forget.py
drkns/context/get_past_execution_status.py
drkns/context/get_unit_step_path.py
drkns/context/store_past_execution_status.py
drkns/context/sync.py
drkns/debug/__init__.py
drkns/debug/get_debug_information.py
drkns/exception/__init__.py
drkns/generation/GenerationTemplate.py
drkns/generation/__init__.py
drkns/generation/_tags.py
drkns/generation/pattern_util.py
drkns/generation/generation/__init__.py
drkns/generation/generation/get_formatted_from_groups_configuration.py
drkns/generation/generation/get_group_block.py
drkns/generation/generation/get_unit_block.py
drkns/generation/templateloading/__init__.py
drkns/generation/templateloading/check_generation_template.py
drkns/generation/templateloading/get_generation_template.py
drkns/generation/templateloading/get_generation_template_path.py
drkns/runner/__init__.py
drkns/runner/get_dependency_groups_configuration.py
drkns/runner/get_execution_plan.py
drkns/runner/get_successful_flag_and_combined_output.py
drkns/runner/remove_execution_plan_redundancies.py
drkns/runner/run.py
drkns/runner/run_plan.py
drkns/step/Step.py
drkns/step/__init__.py
drkns/step/get_step_type.py
drkns/step/step_type.py
drkns/stepexecutionstatus/StepExecutionStatus.py
drkns/stepexecutionstatus/__init__.py
drkns/stepexecutionstatus/get_status_message_and_output_from_status.py
drkns/util/__init__.py
drkns-3.1.2.data/scripts/drkns
drkns-3.1.2.dist-info/METADATA
drkns-3.1.2.dist-info/WHEEL
drkns-3.1.2.dist-info/top_level.txt
drkns-3.1.2.dist-info/RECORD
