Metadata-Version: 2.1
Name: drkns
Version: 3.1.2
Summary: Simple and agnostic monorepo build tool
Home-page: https://github.com/frantzmiccoli/drkns
License: MIT
Keywords: devops build test monorepo cache
Requires-Dist: awscli <2,>=1
Requires-Dist: dirhash <1.0,>=0.2
Requires-Dist: ruamel.yaml >=0.18
